setup.py
Mydistributions.egg-info/PKG-INFO
Mydistributions.egg-info/SOURCES.txt
Mydistributions.egg-info/dependency_links.txt
Mydistributions.egg-info/not-zip-safe
Mydistributions.egg-info/top_level.txt
distributions/Binomialdistribution.py
distributions/Gaussiandistribution.py
distributions/Generaldistribution.py
distributions/__init__.py